{
  "version": "2.0",
  "project_name": "Talents Acting",
  "description": "A talent management platform for actors, comedians, and performers - showcasing profiles, connecting with film professionals, and managing talent databases for the Acting Institute",
  "current_phase": 1,
  "current_session": null,
  "phases": {
    "0": {
      "name": "Foundation",
      "description": "Core infrastructure, database design, authentication, UI framework, talent profiles, and admin dashboard",
      "status": "complete",
      "session_count": 6
    },
    "1": {
      "name": "Talent Management",
      "description": "Advanced filtering, media uploads, search, profile enhancement, and public gallery",
      "status": "in_progress",
      "session_count": 5
    }
  },
  "completed_sessions": [
    "phase00-session01-project_setup",
    "phase00-session02-database_schema",
    "phase00-session03-core_ui_framework",
    "phase00-session04-authentication",
    "phase00-session05-talent_profile_foundation",
    "phase00-session06-admin_dashboard",
    "phase01-session01-advanced_filtering",
    "phase01-session02-media_upload_system"
  ],
  "next_session_history": [
    {
      "date": "2026-01-14",
      "session": "phase00-session01-project_setup",
      "status": "tasks_created"
    },
    {
      "date": "2026-01-14",
      "session": "phase00-session01-project_setup",
      "status": "recommended"
    },
    {
      "date": "2026-01-14",
      "session": "phase00-session01-project_setup",
      "status": "validated"
    },
    {
      "date": "2026-01-14",
      "session": "phase00-session01-project_setup",
      "status": "completed"
    },
    {
      "date": "2026-01-14",
      "session": "phase00-session02-database_schema",
      "status": "recommended"
    },
    {
      "date": "2026-01-14",
      "session": "phase00-session02-database_schema",
      "status": "spec_created"
    },
    {
      "date": "2026-01-14",
      "session": "phase00-session02-database_schema",
      "status": "tasks_created"
    },
    {
      "date": "2026-01-14",
      "session": "phase00-session02-database_schema",
      "status": "validated"
    },
    {
      "date": "2026-01-14",
      "session": "phase00-session02-database_schema",
      "status": "completed"
    },
    {
      "date": "2026-01-14",
      "session": "phase00-session03-core_ui_framework",
      "status": "recommended"
    },
    {
      "date": "2026-01-14",
      "session": "phase00-session03-core_ui_framework",
      "status": "spec_created"
    },
    {
      "date": "2026-01-14",
      "session": "phase00-session03-core_ui_framework",
      "status": "tasks_created"
    },
    {
      "date": "2026-01-14",
      "session": "phase00-session03-core_ui_framework",
      "status": "validated"
    },
    {
      "date": "2026-01-14",
      "session": "phase00-session03-core_ui_framework",
      "status": "completed"
    },
    {
      "date": "2026-01-14",
      "session": "phase00-session04-authentication",
      "status": "recommended"
    },
    {
      "date": "2026-01-14",
      "session": "phase00-session04-authentication",
      "status": "spec_created"
    },
    {
      "date": "2026-01-14",
      "session": "phase00-session04-authentication",
      "status": "tasks_created"
    },
    {
      "date": "2026-01-14",
      "session": "phase00-session04-authentication",
      "status": "validated"
    },
    {
      "date": "2026-01-14",
      "session": "phase00-session04-authentication",
      "status": "completed"
    },
    {
      "date": "2026-01-14",
      "session": "phase00-session05-talent_profile_foundation",
      "status": "recommended"
    },
    {
      "date": "2026-01-14",
      "session": "phase00-session05-talent_profile_foundation",
      "status": "spec_created"
    },
    {
      "date": "2026-01-14",
      "session": "phase00-session05-talent_profile_foundation",
      "status": "tasks_created"
    },
    {
      "date": "2026-01-15",
      "session": "phase00-session05-talent_profile_foundation",
      "status": "validated"
    },
    {
      "date": "2026-01-15",
      "session": "phase00-session05-talent_profile_foundation",
      "status": "completed"
    },
    {
      "date": "2026-01-15",
      "session": "phase00-session06-admin_dashboard",
      "status": "recommended"
    },
    {
      "date": "2026-01-15",
      "session": "phase00-session06-admin_dashboard",
      "status": "spec_created"
    },
    {
      "date": "2026-01-15",
      "session": "phase00-session06-admin_dashboard",
      "status": "tasks_created"
    },
    {
      "date": "2026-01-15",
      "session": "phase00-session06-admin_dashboard",
      "status": "validated"
    },
    {
      "date": "2026-01-15",
      "session": "phase00-session06-admin_dashboard",
      "status": "completed"
    },
    {
      "date": "2026-01-15",
      "session": "phase01-session01-advanced_filtering",
      "status": "recommended"
    },
    {
      "date": "2026-01-15",
      "session": "phase01-session01-advanced_filtering",
      "status": "spec_created"
    },
    {
      "date": "2026-01-15",
      "session": "phase01-session01-advanced_filtering",
      "status": "tasks_created"
    },
    {
      "date": "2026-01-15",
      "session": "phase01-session01-advanced_filtering",
      "status": "validated"
    },
    {
      "date": "2026-01-15",
      "session": "phase01-session01-advanced_filtering",
      "status": "completed"
    },
    {
      "date": "2026-01-15",
      "session": "phase01-session02-media_upload_system",
      "status": "recommended"
    },
    {
      "date": "2026-01-15",
      "session": "phase01-session02-media_upload_system",
      "status": "spec_created"
    },
    {
      "date": "2026-01-15",
      "session": "phase01-session02-media_upload_system",
      "status": "tasks_created"
    },
    {
      "date": "2026-01-15",
      "session": "phase01-session02-media_upload_system",
      "status": "validated"
    },
    {
      "date": "2026-01-15",
      "session": "phase01-session02-media_upload_system",
      "status": "completed"
    }
  ]
}
